pytect/__init__.py
pytect-0.0.1.dist-info/LICENSE.txt
pytect-0.0.1.dist-info/METADATA
pytect-0.0.1.dist-info/WHEEL
pytect-0.0.1.dist-info/top_level.txt
pytect-0.0.1.dist-info/RECORD
